{
    "gui": {
        "editor_opengl": {
            "rel_pos": {
                "__jsonqualname__": "__builtin__.tuple", 
                "items": [
                    19.81236673773987, 
                    -27.530916844349676
                ]
            }, 
            "size": {
                "__jsonqualname__": "__builtin__.tuple", 
                "items": [
                    20.0, 
                    20.0
                ]
            }
        }
    }, 
    "input_data_port4": {
        "gui": {}
    }, 
    "outcome-1": {
        "gui": {}
    }, 
    "outcome-2": {
        "gui": {}
    }, 
    "outcome0": {
        "gui": {}
    }, 
    "output_data_port5": {
        "gui": {}
    }
}